MANIFEST.in
setup.py
authentise_services/__init__.py
authentise_services/config.py
authentise_services/errors.py
authentise_services/model.py
authentise_services/session.py
authentise_services/slice.py
authentise_services/slicing_settings.py
authentise_services/version.json
authentise_services.egg-info/PKG-INFO
authentise_services.egg-info/SOURCES.txt
authentise_services.egg-info/dependency_links.txt
authentise_services.egg-info/requires.txt
authentise_services.egg-info/top_level.txt