Metadata-Version: 1.0
Name: authentise-services
Version: 0.6.0
Summary: A client library for Authentise open services
Home-page: https://github.com/DoWhileGeek/authentise-services
Author: Joeseph Rodrigues
Author-email: dowhilegeek@gmail.com
License: UNKNOWN
Platform: UNKNOWN
